infi.dygraphs-0.14-py3.7-nspkg.pth
infi/dygraphs/__init__.py
infi/dygraphs/__version__.py
infi/dygraphs/static/dygraphs/chart_models.js
infi/dygraphs/static/dygraphs/chart_views.js
infi/dygraphs/static/dygraphs/charts.css
infi/dygraphs/static/dygraphs/dygraph.combined.js
infi/dygraphs/static/dygraphs/formatters.js
infi/dygraphs/static/dygraphs/spin.css
infi/dygraphs/static/dygraphs/spin.js
infi/dygraphs/static/dygraphs/switch_widget.css
infi/dygraphs/templates/dygraphs/all_scripts.html
infi/dygraphs/templates/dygraphs/all_styles.html
infi/dygraphs/templates/dygraphs/underscore_templates.html
infi.dygraphs-0.14.dist-info/METADATA
infi.dygraphs-0.14.dist-info/WHEEL
infi.dygraphs-0.14.dist-info/entry_points.txt
infi.dygraphs-0.14.dist-info/namespace_packages.txt
infi.dygraphs-0.14.dist-info/top_level.txt
infi.dygraphs-0.14.dist-info/RECORD
