Metadata-Version: 2.1
Name: infi.dygraphs
Version: 0.14
Summary: A fork of http://dygraphs.com/ with INFINIDAT-specific customizations and utilities.
Home-page: https://git.infinidat.com/host-internal/infi.dygraphs
Author: Itay Galea
Author-email: igalea@infinidat.com
License: BSD
Platform: UNKNOWN
Classifier: Intended Audience :: Developers
Classifier: Intended Audience :: System Administrators
Classifier: License :: OSI Approved :: BSD License
Classifier: Operating System :: OS Independent
Classifier: Programming Language :: Python
Classifier: Topic :: Software Development :: Libraries :: Python Modules
Requires-Dist: setuptools
